UrbanDictAPI/__init__.py
UrbanDictAPI/defs.py
UrbanDictAPI/main.py
UrbanDictAPI-0.3.dist-info/LICENSE
UrbanDictAPI-0.3.dist-info/METADATA
UrbanDictAPI-0.3.dist-info/WHEEL
UrbanDictAPI-0.3.dist-info/top_level.txt
UrbanDictAPI-0.3.dist-info/RECORD
