Metadata-Version: 2.1
Name: UrbanDictAPI
Version: 0.3
Summary: Unofficial API for the popular website-Urban Dictionary.
Home-page: https://github.com/TanmayArya-1p/UrbanDictAPI
Author: TanmayArya1-p
Author-email: <tanmayarya2018@gmail.com>
License: UNKNOWN
Keywords: python,api,API,web-scraping
Platform: UNKNOWN
Classifier: Intended Audience :: Developers
Classifier: Programming Language :: Python :: 3
Classifier: Operating System :: Unix
Classifier: Operating System :: MacOS :: MacOS X
Classifier: Operating System :: Microsoft :: Windows
Requires-Dist: beautifulsoup4
Requires-Dist: requests
